<virtual-user errorPolicy="DO_NOTHING"
    failedAssertionPolicy="DO_NOTHING" slaProfileEnabled="false" uid="Signin">
    <init-container element-number="1" execution-type="0" pacingEnd="0"
        pacingMode="MODE_NO_PACING" pacingStart="0" pacingValue="0"
        slaProfileEnabled="false" traceVariableNamesAsString="" weightsEnabled="false">
        <description>Elements executed once when the Virtual User starts.</description>
    </init-container>
    <actions-container clearUserIterationDataMode="AUTO"
        element-number="1" execution-type="0" pacingEnd="0"
        pacingMode="MODE_NO_PACING" pacingStart="0" pacingValue="0"
        slaProfileEnabled="false" traceVariableNamesAsString="" weightsEnabled="false">
        <description>Elements repeated until the Virtual User stops.</description>
        <weighted-embedded-action uid="d45c8eb9-f3a6-4118-8cc7-5be588915969"/>
        <weighted-embedded-action uid="b3b53ed5-635f-44cf-84b7-09216a781b1d"/>
        <weighted-embedded-action uid="a23a758b-a9f0-4d42-af11-eaeb8c311203"/>
        <weighted-embedded-action uid="e399d480-b993-4edb-85f7-9d05d0e3aac6"/>
    </actions-container>
    <end-container element-number="1" execution-type="0" pacingEnd="0"
        pacingMode="MODE_NO_PACING" pacingStart="0" pacingValue="0"
        slaProfileEnabled="false" traceVariableNamesAsString="" weightsEnabled="false">
        <description>Elements executed before the Virtual User stops.</description>
    </end-container>
    <thinktime-policy thinkTimeMode="MODE_SIMPLE_THINK_TIME"
        thinktimeFactorValue="100" thinktimePolicy="0"
        thinktimeRangeValue="0" thinktimeValue="5000"/>
</virtual-user>
